{
  "project_info": {
    "project_number": "755165637533",
    "project_id": "alura-esporte-214f1",
    "storage_bucket": "alura-esporte-214f1.appspot.com"
  },
  "client": [
    {
      "client_info": {
        "mobilesdk_app_id": "1:755165637533:android:45032098b3add909c25d74",
        "android_client_info": {
          "package_name": "com.spaceapp"
        }
      },
      "oauth_client": [
        {
          "client_id": "755165637533-j44a2gjrj7ma24aoo3gtsonse53ovp4e.apps.googleusercontent.com",
          "client_type": 3
        }
      ],
      "api_key": [
        {
          "current_key": "AIzaSyCcwKPeY0m99rwMNsaY6-MlrBCpMZO476I"
        }
      ],
      "services": {
        "appinvite_service": {
          "other_platform_oauth_client": [
            {
              "client_id": "755165637533-j44a2gjrj7ma24aoo3gtsonse53ovp4e.apps.googleusercontent.com",
              "client_type": 3
            }
          ]
        }
      }
    }
  ],
  "configuration_version": "1"
}